likepep403/__init__.py
likepep403/abc.py
likepep403/caller.py
likepep403/decor.py
likepep403/missing.py
likepep403-2.0.0.dist-info/LICENSE
likepep403-2.0.0.dist-info/METADATA
likepep403-2.0.0.dist-info/WHEEL
likepep403-2.0.0.dist-info/top_level.txt
likepep403-2.0.0.dist-info/RECORD
