Metadata-Version: 2.1
Name: likepep403
Version: 2.0.0
Summary: A library containing several useful Python decorators, simulating PEP 403's capabilities.
Author: Wojciech Marzec
License: MIT License
Project-URL: repository, https://github.com/Keyacom/likepep403
Keywords: pep403,decorator
Classifier: License :: OSI Approved :: MIT License
Classifier: Programming Language :: Python
Classifier: Typing :: Typed
Classifier: Topic :: Utilities
Requires-Python: >=3.12
License-File: LICENSE
